glyphsets/__init__.py
glyphsets/__main__.py
glyphsets/_version.py
glyphsets/helpers.py
glyphsets/definitions/GF_Arabic_Core.yaml
glyphsets/definitions/GF_Arabic_Plus.yaml
glyphsets/definitions/GF_Cyrillic_Core.yaml
glyphsets/definitions/GF_Cyrillic_Historical.yaml
glyphsets/definitions/GF_Cyrillic_Plus.yaml
glyphsets/definitions/GF_Cyrillic_Pro.yaml
glyphsets/definitions/GF_Greek_AncientMusicalSymbols.yaml
glyphsets/definitions/GF_Greek_Archaic.yaml
glyphsets/definitions/GF_Greek_Coptic.yaml
glyphsets/definitions/GF_Greek_Core.yaml
glyphsets/definitions/GF_Greek_Expert.yaml
glyphsets/definitions/GF_Greek_Plus.yaml
glyphsets/definitions/GF_Greek_Pro.yaml
glyphsets/definitions/GF_Latin_African.yaml
glyphsets/definitions/GF_Latin_Beyond.yaml
glyphsets/definitions/GF_Latin_Core.yaml
glyphsets/definitions/GF_Latin_Kernel.yaml
glyphsets/definitions/GF_Latin_Plus.yaml
glyphsets/definitions/GF_Latin_PriAfrican.yaml
glyphsets/definitions/GF_Latin_Vietnamese.yaml
glyphsets/definitions/GF_Phonetics_APA.yaml
glyphsets/definitions/GF_Phonetics_DisorderedSpeech.yaml
glyphsets/definitions/GF_Phonetics_IPAHistorical.yaml
glyphsets/definitions/GF_Phonetics_IPAStandard.yaml
glyphsets/definitions/GF_Phonetics_SinoExt.yaml
glyphsets/definitions/GF_TransLatin_Arabic.yaml
glyphsets/definitions/GF_TransLatin_Pinyin.yaml
glyphsets/results/nam/GF_Arabic_Core.nam
glyphsets/results/nam/GF_Arabic_Plus.nam
glyphsets/results/nam/GF_Cyrillic_Core.nam
glyphsets/results/nam/GF_Cyrillic_Historical.nam
glyphsets/results/nam/GF_Cyrillic_Plus.nam
glyphsets/results/nam/GF_Cyrillic_Pro.nam
glyphsets/results/nam/GF_Greek_AncientMusicalSymbols.nam
glyphsets/results/nam/GF_Greek_Archaic.nam
glyphsets/results/nam/GF_Greek_Coptic.nam
glyphsets/results/nam/GF_Greek_Core.nam
glyphsets/results/nam/GF_Greek_Expert.nam
glyphsets/results/nam/GF_Greek_Plus.nam
glyphsets/results/nam/GF_Greek_Pro.nam
glyphsets/results/nam/GF_Latin_African.nam
glyphsets/results/nam/GF_Latin_Beyond.nam
glyphsets-1.0.0.dist-info/LICENSE
glyphsets-1.0.0.dist-info/METADATA
glyphsets-1.0.0.dist-info/WHEEL
glyphsets-1.0.0.dist-info/entry_points.txt
glyphsets-1.0.0.dist-info/top_level.txt
glyphsets-1.0.0.dist-info/RECORD
