Metadata-Version: 2.1
Name: glyphsets
Version: 1.0.0
Summary: A python API for evaluating coverage of glyph sets in font projects.
Home-page: https://github.com/googlefonts/glyphsets/
Author: Dave Crossland, Eli Heuer, Felipe Sanches, Lasse Fister, Marc Foley, Yanone, Roderick Sheeter
Author-email: dave@lab6.com
Classifier: Intended Audience :: Developers
Classifier: Topic :: Text Processing :: Fonts
Classifier: License :: OSI Approved :: Apache Software License
Classifier: Operating System :: OS Independent
Classifier: Programming Language :: Python :: 3
Requires-Python: >=3.8
License-File: LICENSE
Requires-Dist: requests
Requires-Dist: setuptools
Requires-Dist: FontTools[ufo]
Requires-Dist: glyphsLib>=6.7.1
Requires-Dist: defcon
Requires-Dist: unicodedata2
Requires-Dist: gflanguages>=0.6.0
Requires-Dist: pyyaml
Provides-Extra: dev
Requires-Dist: gfsubsets; extra == "dev"
